{
  "last_updated": "2026-07-01T20:01:17.283Z",
  "source_count": 3,
  "items": [
    {
      "id": "bon-appetit-0",
      "title": "I'm a Sommelier, So Trust When I Say These Are the Best Wine Subscription Clubs (2026)",
      "summary": "Expand your palate with these wine clubs that drop high-quality bottles right at your doorstep.",
      "link": "https://www.bonappetit.com/story/best-wine-subscriptions",
      "published": "2026-07-01T19:34:16.000Z",
      "source": "Bon Appetit",
      "category": "general",
      "xml_category": "shopping",
      "tags": [],
      "image": "https://assets.bonappetit.com/photos/682e0bbf686ea634c79b858a/master/pass/Best-wine-clubs.jpg"
    },
    {
      "id": "bon-appetit-1",
      "title": "29 No-Cook Dinners for a Summer Heat Wave",
      "summary": "Leveled-up avocado toast, vibrant green gazpacho, filling salads, and more no-oven-needed meals.",
      "link": "https://www.bonappetit.com/recipes/slideshow/summer-recipes-dont-cook",
      "published": "2026-07-01T18:00:00.000Z",
      "source": "Bon Appetit",
      "category": "general",
      "xml_category": "recipes",
      "tags": [],
      "image": "https://assets.bonappetit.com/photos/62b9eeb29c2b5285773bba49/master/pass/0627-sub-salad-recipe-lede.jpg"
    },
    {
      "id": "index-0",
      "title": "Moambe piletina: Najpopularnije je jelo u DR Kongu koje osvaja na prvi zalogaj",
      "summary": "MOAMBE piletina je nacionalno jelo Konga, bogati pileći gulaš s maslacem od kikirikija i palminim uljem. Članak donosi detaljan recept, savjete za pripremu i prijedloge za posluživanje.",
      "link": "https://www.index.hr/food/clanak/moambe-piletina-najpopularnije-je-jelo-u-dr-kongu-koje-osvaja-na-prvi-zalogaj/2808846.aspx",
      "published": "2026-07-01T17:30:00.000Z",
      "source": "Index",
      "category": "general",
      "xml_category": "food",
      "tags": [],
      "image": null
    },
    {
      "id": "index-1",
      "title": "Odmah bacite krastavce ako na njima primijetite nekoliko stvari",
      "summary": "KRASTAVCI se brzo kvare zbog puno vode.",
      "link": "https://www.index.hr/food/clanak/odmah-bacite-krastavce-ako-na-njima-primijetite-nekoliko-stvari/2808795.aspx",
      "published": "2026-07-01T14:57:00.000Z",
      "source": "Index",
      "category": "general",
      "xml_category": "food",
      "tags": [],
      "image": null
    },
    {
      "id": "index-2",
      "title": "Otkriveno koju su hranu Hrvati najviše naručivali uoči utakmice s Ganom",
      "summary": "BURGERI, krumpirići i pizza bili su najpopularniji izbori u gradovima poput Zagreba i Splita.",
      "link": "https://www.index.hr/food/clanak/otkriveno-koju-su-hranu-hrvati-najvise-narucivali-uoci-utakmice-s-ganom/2808783.aspx",
      "published": "2026-07-01T14:34:00.000Z",
      "source": "Index",
      "category": "general",
      "xml_category": "food",
      "tags": [],
      "image": null
    },
    {
      "id": "index-3",
      "title": "Jeste li znali da vam za domaći sladoled treba samo blender? Prejednostavno je",
      "summary": "RECEPT za brz i osvježavajuć domaći sladoled od smrznutog šumskog voća.",
      "link": "https://www.index.hr/food/clanak/jeste-li-znali-da-vam-za-domaci-sladoled-treba-samo-blender-prejednostavno-je/2808776.aspx",
      "published": "2026-07-01T14:16:00.000Z",
      "source": "Index",
      "category": "general",
      "xml_category": "food",
      "tags": [],
      "image": null
    },
    {
      "id": "index-4",
      "title": "Znakovi koji otkrivaju da se lubenica pokvarila",
      "summary": "LUBENICA je ljetno osvježenje, no važno je znati prepoznati kada se pokvarila.",
      "link": "https://www.index.hr/food/clanak/znakovi-koji-otkrivaju-da-se-lubenica-pokvarila/2808750.aspx",
      "published": "2026-07-01T13:33:00.000Z",
      "source": "Index",
      "category": "general",
      "xml_category": "food",
      "tags": [],
      "image": null
    },
    {
      "id": "index-5",
      "title": "Našli ste pljesnivu borovnicu u kutiji - treba li baciti cijelo pakiranje?",
      "summary": "JEDNA pljesniva bobica ne znači nužno da morate baciti cijelo pakiranje.",
      "link": "https://www.index.hr/food/clanak/nasli-ste-pljesnivu-borovnicu-u-kutiji-treba-li-baciti-cijelo-pakiranje/2808743.aspx",
      "published": "2026-07-01T12:58:00.000Z",
      "source": "Index",
      "category": "general",
      "xml_category": "food",
      "tags": [],
      "image": null
    },
    {
      "id": "index-6",
      "title": "Lazanje se u Napulju rade malo drugačije (i zvuče nevjerojatno)",
      "summary": "RAZLIKUJU se od klasičnih po ricotti, mesnim okruglicama i kuhanim jajima, a priprema traje satima.",
      "link": "https://www.index.hr/food/clanak/lazanje-se-u-napulju-rade-malo-drugacije-i-zvuce-nevjerojatno/2808733.aspx",
      "published": "2026-07-01T12:56:00.000Z",
      "source": "Index",
      "category": "general",
      "xml_category": "food",
      "tags": [],
      "image": null
    },
    {
      "id": "bon-appetit-2",
      "title": "The Ultimate Guide to American Barbecue Culture",
      "summary": "Explore the past, present, and future of American barbecue, from regional histories to the next generation of pitmasters rewriting the rules.",
      "link": "https://www.bonappetit.com/story/america-250-barbecue-guide",
      "published": "2026-07-01T12:09:56.000Z",
      "source": "Bon Appetit",
      "category": "general",
      "xml_category": "culture",
      "tags": [],
      "image": "https://assets.bonappetit.com/photos/6a3afb7b1123db63c9f0fa09/master/pass/america-the-barbecue_LEDE_V6_061026_5760_VOG_final.jpg"
    },
    {
      "id": "index-7",
      "title": "Čitateljica kaže da je ovaj neobičan cheesecake - savršen",
      "summary": "RECEPT za osvježavajući ljetni desert bez pečenja.",
      "link": "https://www.index.hr/food/clanak/citateljica-kaze-da-je-ovaj-neobican-cheesecake-savrsen/2808713.aspx",
      "published": "2026-07-01T12:05:00.000Z",
      "source": "Index",
      "category": "general",
      "xml_category": "food",
      "tags": [],
      "image": null
    },
    {
      "id": "bon-appetit-3",
      "title": "The Best Barbecue Gear for You, No Matter Your Experience Level",
      "summary": "Professional pitmasters on what you need for every era of your barbecue journey",
      "link": "https://www.bonappetit.com/story/grilling-gear-upgrades",
      "published": "2026-07-01T12:01:00.000Z",
      "source": "Bon Appetit",
      "category": "general",
      "xml_category": "shopping",
      "tags": [],
      "image": "https://assets.bonappetit.com/photos/6a3eb541b53ff730762cd736/master/pass/BBQ-Commerce-Tools-Lede-LE_4x5.gif"
    },
    {
      "id": "bon-appetit-4",
      "title": "Pickle Coleslaw",
      "summary": "Creamy, vinegary, and with lots of fresh dill.",
      "link": "https://www.bonappetit.com/recipe/pickle-coleslaw",
      "published": "2026-07-01T12:00:00.000Z",
      "source": "Bon Appetit",
      "category": "general",
      "xml_category": "recipes",
      "tags": [],
      "image": "https://assets.bonappetit.com/photos/6a3ae5b61412881419996f75/master/pass/pickle-coleslaw_RECIPE_V3_060926_5410_VOG_final.jpg"
    },
    {
      "id": "bon-appetit-5",
      "title": "Pickle Lemonade",
      "summary": "Country-style lemonade with a salty-tangy twist.",
      "link": "https://www.bonappetit.com/recipe/pickle-lemonade",
      "published": "2026-07-01T12:00:00.000Z",
      "source": "Bon Appetit",
      "category": "general",
      "xml_category": "recipes",
      "tags": [],
      "image": "https://assets.bonappetit.com/photos/6a3ae5e72ad1f98c2a0fc9ac/master/pass/pickle-lemonade_RECIPE_V1_060926_5457_VOG_final.jpg"
    },
    {
      "id": "bon-appetit-6",
      "title": "Mapping a Barbecue Sauce Trail Through the Carolinas",
      "summary": "Tradition and evolving influences have resulted in a diversity of sauces across North and South Carolina. Here’s where to find them.",
      "link": "https://www.bonappetit.com/story/carolina-barbecue-sauce-trail",
      "published": "2026-07-01T12:00:00.000Z",
      "source": "Bon Appetit",
      "category": "ai",
      "xml_category": "culture",
      "tags": [],
      "image": "https://assets.bonappetit.com/photos/6a4505502a46f42d14092c1a/master/pass/BBQ_SauceTrail_LEDE-Thumb.gif"
    },
    {
      "id": "bon-appetit-7",
      "title": "Heidi Gardner Is Kansas City Barbecue’s Loudest Cheerleader",
      "summary": "The former SNL star waxes poetic on burnt ends, barbecue sauce, and white bread",
      "link": "https://www.bonappetit.com/story/heidi-gardner-kansas-city-barbecue",
      "published": "2026-07-01T12:00:00.000Z",
      "source": "Bon Appetit",
      "category": "general",
      "xml_category": "restaurants",
      "tags": [],
      "image": "https://assets.bonappetit.com/photos/6a3bf81bc62f0c031e728bbe/master/pass/20260427_DRE_000098.jpg"
    },
    {
      "id": "bon-appetit-8",
      "title": "Finding Forgiveness at the Barbecue Counter",
      "summary": "My father’s stories about his Southern upbringing were fraught, but his love of barbecue helped me find tenderness in the tension.",
      "link": "https://www.bonappetit.com/story/finding-forgiveness-at-the-barbecue-counter",
      "published": "2026-07-01T12:00:00.000Z",
      "source": "Bon Appetit",
      "category": "general",
      "xml_category": "culture",
      "tags": [],
      "image": "https://assets.bonappetit.com/photos/6a3eae525fce68349be10aac/master/pass/BBQ_ComingToTerms_LEDE-16x9.png"
    },
    {
      "id": "bon-appetit-9",
      "title": "Burger Beans (Baked Beans With Ground Beef)",
      "summary": "A beefed-up take on a BBQ staple.",
      "link": "https://www.bonappetit.com/recipe/burger-beans-baked-beans-ground-beef",
      "published": "2026-07-01T12:00:00.000Z",
      "source": "Bon Appetit",
      "category": "general",
      "xml_category": "recipes",
      "tags": [],
      "image": "https://assets.bonappetit.com/photos/6a3ae597daa7a5ccf5304781/master/pass/burger-beans_RECIPE_V4_060926_5383_VOG_final.jpg"
    },
    {
      "id": "bon-appetit-10",
      "title": "Banana Pudding Cake",
      "summary": "Brown-butter banana cake with banana cream and crunchy vanilla wafers for good measure.",
      "link": "https://www.bonappetit.com/recipe/banana-pudding-cake",
      "published": "2026-07-01T12:00:00.000Z",
      "source": "Bon Appetit",
      "category": "general",
      "xml_category": "recipes",
      "tags": [],
      "image": "https://assets.bonappetit.com/photos/6a3ae565cf1e780d61965f92/master/pass/banana-pudding-cake_RECIPE_V5_060926_5512_VOG_final.jpg"
    },
    {
      "id": "bon-appetit-11",
      "title": "Ensalada Rusa (Pink Potato Salad)",
      "summary": "This Caribbean classic, made with beets for a magenta hue, looks as striking as it tastes.",
      "link": "https://www.bonappetit.com/recipe/ensalada-rusa-pink-potato-salad",
      "published": "2026-07-01T12:00:00.000Z",
      "source": "Bon Appetit",
      "category": "general",
      "xml_category": "recipes",
      "tags": [],
      "image": "https://assets.bonappetit.com/photos/6a3ae60a8b87615c097a3768/master/pass/pink-potato-salad_RECIPE_V1_060926_5607_VOG_final.jpg"
    },
    {
      "id": "bon-appetit-12",
      "title": "A Better Beer Can Chicken",
      "summary": "Use the beer, not the can, for this citrusy take on a classic that nods to mojo criollo.",
      "link": "https://www.bonappetit.com/recipe/better-beer-can-chicken",
      "published": "2026-07-01T12:00:00.000Z",
      "source": "Bon Appetit",
      "category": "general",
      "xml_category": "recipes",
      "tags": [],
      "image": "https://assets.bonappetit.com/photos/6a3ae69ab032576f890c39b5/master/pass/better-than-beer-can-chicken_IG_V2_061026_5685_V1_final.jpg"
    },
    {
      "id": "bon-appetit-13",
      "title": "23 Easy Weeknight Dinners for July 2026",
      "summary": "Hot honey salmon, teriyaki chicken, the best gazpacho, and more quick dinners to make this month.",
      "link": "https://www.bonappetit.com/gallery/easy-weeknight-dinner-recipes",
      "published": "2026-07-01T12:00:00.000Z",
      "source": "Bon Appetit",
      "category": "general",
      "xml_category": "recipes",
      "tags": [],
      "image": "https://assets.bonappetit.com/photos/63697c68b9059ede9a674e7f/master/pass/1107-chicken-teriyaki-lede.jpg"
    },
    {
      "id": "bon-appetit-14",
      "title": "A Cookout Menu That’s as Breezy as Summer",
      "summary": "From beer-marinated chicken to smoky burger beans and pickle-packed slaw, this menu dials up beloved classics.",
      "link": "https://www.bonappetit.com/story/breezy-summer-cookout-menu",
      "published": "2026-07-01T12:00:00.000Z",
      "source": "Bon Appetit",
      "category": "general",
      "xml_category": "cooking",
      "tags": [],
      "image": "https://assets.bonappetit.com/photos/6a3afb7bc7f46fcfae09b171/master/pass/america-the-barbecue_LEDE_V4_061026_5737_VOG_final.jpg"
    },
    {
      "id": "bon-appetit-15",
      "title": "Meet the New Guard of American Barbecue",
      "summary": "From Thai-spiced brisket in Kansas City to a pernil-powered menu in Charleston, this cohort of chefs is rewriting the rules of traditional ’cue.",
      "link": "https://www.bonappetit.com/story/third-wave-barbecue",
      "published": "2026-07-01T12:00:00.000Z",
      "source": "Bon Appetit",
      "category": "general",
      "xml_category": "culture",
      "tags": [],
      "image": "https://assets.bonappetit.com/clips/6a3c5fdfcda82aa8207c989f/master/pass/third-wave-barbecue_LEDE_V2_final.mp4"
    },
    {
      "id": "bon-appetit-16",
      "title": "Inside the High-Stakes Competition of the World Championship Barbecue Cooking Contest",
      "summary": "At the World Championship Barbecue Cooking Contest, the only thing hotter than the smokers is the pitmasters’ drive to win.",
      "link": "https://www.bonappetit.com/story/memphis-barbecue-championship",
      "published": "2026-07-01T12:00:00.000Z",
      "source": "Bon Appetit",
      "category": "general",
      "xml_category": "culture",
      "tags": [],
      "image": "https://assets.bonappetit.com/photos/6a3d50a880721c3fcd111334/master/pass/BonAppetite_BBQ_Final-26.jpg"
    },
    {
      "id": "bon-appetit-17",
      "title": "Tech Is Coming for One of the Oldest Forms of Cooking",
      "summary": "Cooking with live fire? There's an app for that.",
      "link": "https://www.bonappetit.com/story/grilling-gets-smart-technology",
      "published": "2026-07-01T12:00:00.000Z",
      "source": "Bon Appetit",
      "category": "tech",
      "xml_category": "shopping",
      "tags": [],
      "image": "https://assets.bonappetit.com/photos/6a3eb541a62e8ee6392adc70/master/pass/BBQ-Commerce-Lede-LE-3-4x5.gif"
    },
    {
      "id": "bon-appetit-18",
      "title": "How Central Texas Barbecue Came to Rule the World",
      "summary": "There's seemingly no stopping the spread of the Lone Star State's signature barbecue, which is shaping menus from Miami to Cairo.",
      "link": "https://www.bonappetit.com/story/central-texas-barbecue",
      "published": "2026-07-01T12:00:00.000Z",
      "source": "Bon Appetit",
      "category": "general",
      "xml_category": "culture",
      "tags": [],
      "image": "https://assets.bonappetit.com/photos/6a3d6618a9bed2443fb3f681/master/pass/130_BonAppetit_BarbsBQ_MaryKang.JPG"
    },
    {
      "id": "index-8",
      "title": "3 top ljetna kolača s kokosom - superbrza i bez pečenja",
      "summary": "TRI RECEPTA za brze i osvježavajuće ljetne deserte s kokosom koji se ne peku.",
      "link": "https://www.index.hr/food/clanak/3-top-ljetna-kolaca-s-kokosom-superbrza-i-bez-pecenja/2808687.aspx",
      "published": "2026-07-01T11:25:00.000Z",
      "source": "Index",
      "category": "general",
      "xml_category": "food",
      "tags": [],
      "image": null
    },
    {
      "id": "bon-appetit-19",
      "title": "Sweet Corn Butter Mochi With Coconut Crunch",
      "summary": "This summery cake from Bake Club just happens to be gluten-free.",
      "link": "https://www.bonappetit.com/recipe/sweet-corn-butter-mochi-coconut-crunch",
      "published": "2026-07-01T11:00:00.000Z",
      "source": "Bon Appetit",
      "category": "general",
      "xml_category": "recipes",
      "tags": [],
      "image": "https://assets.bonappetit.com/photos/6a20f71b90832f702f69a02f/master/pass/sweet-corn-coconut-crunch-butter-mochi-cake_RECIPE_V3_060326_4690_VOG_Badge_final.jpg"
    },
    {
      "id": "bon-appetit-19",
      "title": "BA Bake Club’s July Recipe Turns Summer Corn Into a Delightfully Bouncy Dessert",
      "summary": "Shilpa’s gluten-free mochi cake packs in nearly a pound of sweet summer corn under a crunchy coconut topping.",
      "link": "https://www.bonappetit.com/story/bake-club",
      "published": "2026-07-01T11:00:00.000Z",
      "source": "Bon Appetit",
      "category": "general",
      "xml_category": "cooking",
      "tags": [],
      "image": "https://assets.bonappetit.com/photos/6a20f71b899636abef37cc9e/master/pass/sweet-corn-coconut-crunch-butter-mochi-cake_LEDE_V1_060326_4674_VOG_Badge_final.jpg"
    },
    {
      "id": "index-9",
      "title": "Tacosi s mljevenom piletinom, brz ručak gotov u manje od pola sata",
      "summary": "RECEPT za brze i ukusne tacose s mljevenom piletinom, grahom i rajčicom.",
      "link": "https://www.index.hr/food/clanak/tacosi-s-mljevenom-piletinom-brz-rucak-gotov-u-manje-od-pola-sata/2808670.aspx",
      "published": "2026-07-01T10:58:00.000Z",
      "source": "Index",
      "category": "general",
      "xml_category": "food",
      "tags": [],
      "image": null
    },
    {
      "id": "index-2",
      "title": "Ručak gotov u pola sata: Brzi i ukusni tacosi s mljevenom piletinom",
      "summary": "RECEPT za brze i ukusne tacose s mljevenom piletinom, grahom i rajčicom.",
      "link": "https://www.index.hr/food/clanak/rucak-gotov-u-pola-sata-brzi-i-ukusni-tacosi-s-mljevenom-piletinom/2808670.aspx",
      "published": "2026-07-01T10:58:00.000Z",
      "source": "Index",
      "category": "general",
      "xml_category": "food",
      "tags": [],
      "image": null
    },
    {
      "id": "index-10",
      "title": "Objavljena je lista najboljih barova u Europi, u top 10 je i jedan iz susjedstva",
      "summary": "POBJEDNIK je atenski Line, a na listi dominiraju barovi iz Atene, Londona i Italije.",
      "link": "https://www.index.hr/food/clanak/objavljena-je-lista-najboljih-barova-u-europi-u-top-10-je-i-jedan-iz-susjedstva/2808646.aspx",
      "published": "2026-07-01T10:20:00.000Z",
      "source": "Index",
      "category": "general",
      "xml_category": "food",
      "tags": [],
      "image": null
    },
    {
      "id": "index-11",
      "title": "Maslinovo ulje i limun: Čudotvorni napitak ili samo mit?",
      "summary": "NAPITAK od maslinova ulja i limuna popularan je za zdravlje.",
      "link": "https://www.index.hr/food/clanak/maslinovo-ulje-i-limun-cudotvorni-napitak-ili-samo-mit/2808635.aspx",
      "published": "2026-07-01T09:55:00.000Z",
      "source": "Index",
      "category": "tech",
      "xml_category": "food",
      "tags": [],
      "image": null
    },
    {
      "id": "index-1",
      "title": "Biste li pili ovakav napitak ujutro? Dva sastojka koja su navodno jako dobra",
      "summary": "NAPITAK od maslinova ulja i limuna popularan je za zdravlje.",
      "link": "https://www.index.hr/food/clanak/biste-li-pili-ovakav-napitak-ujutro-dva-sastojka-koja-su-navodno-jako-dobra/2808635.aspx",
      "published": "2026-07-01T09:55:00.000Z",
      "source": "Index",
      "category": "tech",
      "xml_category": "food",
      "tags": [],
      "image": null
    },
    {
      "id": "index-12",
      "title": "Hit potez sarajevskog kafića uoči utakmice sa SAD-om: Danas na meniju nema Americana",
      "summary": "SARAJEVSKI Spazio Caffé objavio je da na dan utakmice šesnaestine finala SP-a između BiH i SAD-a neće posluživati kavu Americano.",
      "link": "https://www.index.hr/food/clanak/hit-potez-sarajevskog-kafica-uoci-utakmice-sa-sadom-danas-na-meniju-nema-americana/2808629.aspx",
      "published": "2026-07-01T09:42:00.000Z",
      "source": "Index",
      "category": "general",
      "xml_category": "food",
      "tags": [],
      "image": null
    },
    {
      "id": "index-0",
      "title": "Iz sarajevskog kafića poručili: Danas ne poslužujemo Americano kavu",
      "summary": "SARAJEVSKI Spazio Caffé objavio je da na dan utakmice šesnaestine finala SP-a između BiH i SAD-a neće posluživati kavu Americano.",
      "link": "https://www.index.hr/food/clanak/iz-sarajevskog-kafica-porucili-danas-ne-posluzujemo-americano-kavu/2808629.aspx",
      "published": "2026-07-01T09:42:00.000Z",
      "source": "Index",
      "category": "general",
      "xml_category": "food",
      "tags": [],
      "image": null
    },
    {
      "id": "index-13",
      "title": "Objavljene cijene hrane i pića na Wimbledonu. Ljude najviše iznenadilo jedno pravilo",
      "summary": "OBJAVLJENI su jelovnici i cijene za Wimbledon 2026.",
      "link": "https://www.index.hr/food/clanak/objavljene-cijene-hrane-i-pica-na-wimbledonu-ljude-najvise-iznenadilo-jedno-pravilo/2808602.aspx",
      "published": "2026-07-01T09:20:00.000Z",
      "source": "Index",
      "category": "general",
      "xml_category": "food",
      "tags": [],
      "image": null
    },
    {
      "id": "index-14",
      "title": "Tajna savršeno karameliziranog luka: Izbjegnite ključnu pogrešku pri rezanju",
      "summary": "ZA SAVRŠENU karamelizaciju, luk nemojte rezati pretanko jer će zagorjeti.",
      "link": "https://www.index.hr/food/clanak/tajna-savrseno-karameliziranog-luka-izbjegnite-kljucnu-pogresku-pri-rezanju/2808585.aspx",
      "published": "2026-07-01T08:41:00.000Z",
      "source": "Index",
      "category": "general",
      "xml_category": "food",
      "tags": [],
      "image": null
    },
    {
      "id": "index-15",
      "title": "Kupili ste sir koji nema okus po siru? Što je to ustvari i zašto se to događa",
      "summary": "SVE ČEŠĆE na policama nailazimo na sireve koji izgledaju poznato, ali okusom i mirisom ne podsjećaju na ono što očekujemo.",
      "link": "https://www.index.hr/food/clanak/kupili-ste-sir-koji-nema-okus-po-siru-sto-je-to-ustvari-i-zasto-se-to-dogadja/2808586.aspx",
      "published": "2026-07-01T08:41:00.000Z",
      "source": "Index",
      "category": "general",
      "xml_category": "food",
      "tags": [],
      "image": null
    },
    {
      "id": "index-16",
      "title": "Tost s bosiljkom, mozzarellom i rajčicama. Brzi obrok gotov za 15 minuta",
      "summary": "JEDNOSTAVAN recept za tost inspiriran caprese salatom.",
      "link": "https://www.index.hr/food/clanak/tost-s-bosiljkom-mozzarellom-i-rajcicama-brzi-obrok-gotov-za-15-minuta/2808565.aspx",
      "published": "2026-07-01T08:10:00.000Z",
      "source": "Index",
      "category": "general",
      "xml_category": "food",
      "tags": [],
      "image": null
    },
    {
      "id": "jutarnji-0",
      "title": "Izašla je lista najboljih barova u Europi: niti jedan regionalni bar nije se našao na popisu",
      "summary": "Objavljena je inauguralna lista Europe’s 50 Best Bars 2026, novo regionalno izdanje organizacije 50 Best, a nagrade su dodijeljene na ceremoniji održanoj u Amsterdamu 30. lipnja. Riječ je o prvom zasebnom europskom izboru najboljih barova, što je važno jer 50 Best time barsku scenu kontinenta prvi p",
      "link": "https://www.jutarnji.hr/dobrahrana/price/izasla-je-lista-najboljih-barova-u-europi-niti-jedan-regionalni-bar-nije-se-nasao-na-popisu-15723624",
      "published": "2026-07-01T08:07:00.000Z",
      "source": "Jutarnji",
      "category": "general",
      "xml_category": "priče",
      "tags": [],
      "image": "https://media.jutarnji.hr/images/slike/2026/07/01/f_38533908_1280.jpg?1782931442"
    },
    {
      "id": "jutarnji-0",
      "title": "Izašla je lista najboljih barova u Europi, ali nema ni jednog regionalnog koktel bara",
      "summary": "Objavljena je inauguralna lista Europe’s 50 Best Bars 2026, novo regionalno izdanje organizacije 50 Best, a nagrade su dodijeljene na ceremoniji održanoj u Amsterdamu 30. lipnja. Riječ je o prvom zasebnom europskom izboru najboljih barova, što je važno jer 50 Best time barsku scenu kontinenta prvi p",
      "link": "https://www.jutarnji.hr/dobrahrana/price/izasla-je-lista-najboljih-barova-u-europi-ali-nema-ni-jednog-regionalnog-koktel-bara-15723624",
      "published": "2026-07-01T08:07:00.000Z",
      "source": "Jutarnji",
      "category": "general",
      "xml_category": "priče",
      "tags": [],
      "image": "https://media.jutarnji.hr/images/slike/2026/07/01/f_38533908_1280.jpg?1782893335"
    },
    {
      "id": "index-17",
      "title": "Espresso bomb: Novi ljetni hit s TikToka za sve ljubitelje kave",
      "summary": "DRUŠTVENIM mrežama širi se \"espresso bomb\", bezalkoholni ljetni napitak od espressa i tonika.",
      "link": "https://www.index.hr/food/clanak/espresso-bomb-novi-ljetni-hit-s-tiktoka-za-sve-ljubitelje-kave/2808536.aspx",
      "published": "2026-07-01T07:34:00.000Z",
      "source": "Index",
      "category": "general",
      "xml_category": "food",
      "tags": [],
      "image": null
    },
    {
      "id": "index-18",
      "title": "Nekad je bila hrana za siromašne, danas je ponovno tražena",
      "summary": "CIKORIJA se posljednjih godina vraća na jelovnike, a njezina prepoznatljiva gorčina osvaja sve više ljubitelja dobre hrane.",
      "link": "https://www.index.hr/food/clanak/nekad-je-bila-hrana-za-siromasne-danas-je-ponovno-trazena/2808513.aspx",
      "published": "2026-07-01T07:05:00.000Z",
      "source": "Index",
      "category": "general",
      "xml_category": "food",
      "tags": [],
      "image": null
    },
    {
      "id": "jutarnji-1",
      "title": "Poznata pivovara ima novo sour pivo koje donosi neobičnu kombinaciju - pašku sol i korčulansko grožđe",
      "summary": "Jako volimo sour piva, osobito ljeti. Za razliku od običnih lagera ili aleova kod kojih prevladava gorčina, ova se namjerno proizvode tako da razviju osvježavajuće kisele note koje nam pašu posebno ljeti. Okusom mogu podsjećati na razno voće, jogurt ili čak vino. --- Garden Brewery/ --- Nas je poseb",
      "link": "https://www.jutarnji.hr/dobrahrana/dobri-savjeti/poznata-pivovara-ima-novo-sour-pivo-koje-donosi-neobicnu-kombinaciju-pasku-sol-i-korculansko-grozde-15723591",
      "published": "2026-07-01T06:46:00.000Z",
      "source": "Jutarnji",
      "category": "general",
      "xml_category": "dobri savjeti",
      "tags": [],
      "image": "https://media.jutarnji.hr/images/slike/2026/06/25/f_39161667_1280.png?1782931442"
    },
    {
      "id": "jutarnji-2",
      "title": "Ove subote vinari i lokalni OPG-ovi okupljaju se na atraktivnoj manifestaciji uz jela osmišljena kao pratnja vrhunskim vinima",
      "summary": "Wine Summer vraća se na zelinske brege ove subote, 4. srpnja, kada će se u Vinariji Puhelek Purek ponovno okupiti vinari, lokalni proizvođači hrane i posjetitelji zainteresirani za eno-gastro događanja na kontinentu. Manifestacija i ove godine spaja vino, gastronomiju i glazbeni program u ambijentu.",
      "link": "https://www.jutarnji.hr/dobrahrana/price/ove-subote-vinari-i-lokalni-opg-ovi-okupljaju-se-na-atraktivnoj-manifestaciji-uz-jela-osmisljena-kao-pratnja-vrhunskim-vinima-15723589",
      "published": "2026-07-01T06:44:00.000Z",
      "source": "Jutarnji",
      "category": "general",
      "xml_category": "priče",
      "tags": [],
      "image": "https://media.jutarnji.hr/images/slike/2026/06/30/f_39185971_1280.jpg?1782931442"
    },
    {
      "id": "index-19",
      "title": "Rusi i Ukrajinci jedu ovakve palačinke - i vi ih morate probati",
      "summary": "SIRNIKI su mekane palačinke od svježeg sira, idealne za brzi doručak ili desert.",
      "link": "https://www.index.hr/food/clanak/rusi-i-ukrajinci-jedu-ovakve-palacinke-i-vi-ih-morate-probati/2808509.aspx",
      "published": "2026-07-01T06:30:00.000Z",
      "source": "Index",
      "category": "general",
      "xml_category": "food",
      "tags": [],
      "image": null
    },
    {
      "id": "jutarnji-3",
      "title": "Sve što vam za svjetski dobru šalicu filter kave treba je grijalo, komad plastike i, naravno, kava",
      "summary": "Ako kod kuće želite ozbiljno upoznati kavu, ne treba vam cijeli arsenal opreme. Za početak su dovoljni Hario V60 (plastični filter, koji možete kupiti za manje od 10 eura), grijač za vodu i kvalitetna kava. Mlinac, bolja voda i precizna vaga svakako podižu rezultat, ali to su nadogradnje, a ne predu",
      "link": "https://www.jutarnji.hr/dobrahrana/dobri-savjeti/sve-sto-vam-za-svjetski-dobru-salicu-filter-kave-treba-je-grijalo-komad-plastike-i-naravno-kava-15723572",
      "published": "2026-07-01T05:18:00.000Z",
      "source": "Jutarnji",
      "category": "general",
      "xml_category": "dobri savjeti",
      "tags": [],
      "image": "https://media.jutarnji.hr/images/slike/2026/06/17/f_39122265_1280.jpg?1782931442"
    },
    {
      "id": "jutarnji-4",
      "title": "Bili smo na placu, našli najslađe marelice i donjeli vam nekoliko odličnih ideja kako ih iskoristiti",
      "summary": "Na placu je onaj poznati ljetni žamor koji se ne može glumiti ni nadomjestiti. Sve miriše na zrelo voće, drvene gajbice pune su boja, a prodavači vam dok se ni ne snađete uvale komad voća u ruku da “probaš pa ćeš vidjet”. I baš tu, među štandovima gdje se sve lijepi od sunca i šećera, marelice uvije",
      "link": "https://www.jutarnji.hr/dobrahrana/recepti/bili-smo-na-placu-nasli-najslade-marelice-i-donjeli-vam-nekoliko-odlicnih-ideja-kako-ih-iskoristiti-15723568",
      "published": "2026-07-01T05:00:35.000Z",
      "source": "Jutarnji",
      "category": "general",
      "xml_category": "recepti",
      "tags": [],
      "image": "https://media.jutarnji.hr/images/slike/2026/06/30/f_39186532_1280.png?1782931442"
    },
    {
      "id": "bon-appetit-19",
      "title": "Everything BA Editors Tried, Tasted, and Loved in June",
      "summary": "Like pizza-flavored crackers, an outdoor grill for small yards, and comfy sandals for your farmers market jaunts.",
      "link": "https://www.bonappetit.com/story/what-editors-loved-june-2026",
      "published": "2026-06-30T21:41:02.000Z",
      "source": "Bon Appetit",
      "category": "general",
      "xml_category": "shopping",
      "tags": [],
      "image": "https://assets.bonappetit.com/photos/6a443638b979d1754f4fe685/master/pass/June%20Eds%20Picks.jpg"
    },
    {
      "id": "index-19",
      "title": "Kada zamijeniti lonce i tave: Znakovi i savjeti za zbrinjavanje",
      "summary": "KAKO prepoznati znakove istrošenosti na posuđu, poput hrđe, iskrivljenja ili oštećenog premaza.",
      "link": "https://www.index.hr/food/clanak/kada-zamijeniti-lonce-i-tave-znakovi-i-savjeti-za-zbrinjavanje/2808432.aspx",
      "published": "2026-06-30T20:57:00.000Z",
      "source": "Index",
      "category": "general",
      "xml_category": "food",
      "tags": [],
      "image": null
    },
    {
      "id": "index-17",
      "title": "Jednostavna metoda za savršena tvrdo kuhana jaja - koja se lako gule",
      "summary": "OTKRIJTE metodu za savršeno tvrdo kuhana jaja.",
      "link": "https://www.index.hr/food/clanak/jednostavna-metoda-za-savrsena-tvrdo-kuhana-jaja-koja-se-lako-gule/2808426.aspx",
      "published": "2026-06-30T20:35:00.000Z",
      "source": "Index",
      "category": "general",
      "xml_category": "food",
      "tags": [],
      "image": null
    },
    {
      "id": "index-18",
      "title": "Kako najlakše izvaditi koštice iz trešanja bez nereda",
      "summary": "UZGAJIVAČICA trešanja otkriva najbolje vrijeme za čišćenje trešanja.",
      "link": "https://www.index.hr/food/clanak/kako-najlakse-izvaditi-kostice-iz-tresanja-bez-nereda/2808417.aspx",
      "published": "2026-06-30T20:10:00.000Z",
      "source": "Index",
      "category": "general",
      "xml_category": "food",
      "tags": [],
      "image": null
    }
  ]
}