{
  "last_updated": "2026-06-16T09:01:14.356Z",
  "source_count": 3,
  "items": [
    {
      "id": "index-0",
      "title": "Najbolje sorte rajčica za savršeni sendvič",
      "summary": "NAUČITE odabrati idealnu rajčicu za sendvič.",
      "link": "https://www.index.hr/food/clanak/najbolje-sorte-rajcica-za-savrseni-sendvic/2803349.aspx",
      "published": "2026-06-16T08:45:00.000Z",
      "source": "Index",
      "category": "general",
      "xml_category": "food",
      "tags": [],
      "image": null
    },
    {
      "id": "jutarnji-0",
      "title": "Uskoro kreće ljetno Fuliranje, hranu pripremaju neki od naših najpoznatijih kuhara, evo što će se nuditi",
      "summary": "Od 29. lipnja do 5. srpnja zagrebački Trg Josipa Jurja Strossmayera ponovno postaje mjesto gdje se mogu i žele okupljati svi željni dobrog društva, hrane i atmosfere. Upravo tamo i dana kreće Fuliranje Summer Oasis, koje će trajati sedam dana i u sklopu kojeg će ponovno, kao i na brojnim Fuliranjima",
      "link": "https://www.jutarnji.hr/dobrahrana/price/uskoro-krece-ljetno-fuliranje-hranu-pripremaju-neki-od-nasih-najpoznatijih-kuhara-evo-sto-ce-se-nuditi-15718633",
      "published": "2026-06-16T08:22:00.000Z",
      "source": "Jutarnji",
      "category": "general",
      "xml_category": "priče",
      "tags": [],
      "image": "https://media.jutarnji.hr/images/slike/2026/06/16/f_39117213_1280.jpg?1781599821"
    },
    {
      "id": "jutarnji-1",
      "title": "Nisu samo za grickanje: namazi i paste od pistacije su super, ali ovo je još jeftinije i bolje",
      "summary": "Iako je Dubai čokolada donedavno bila ogroman hit, a tiramisu i rolice s pistacijama uvijek i svugdje se rasprodaju prvi, pa čak i ako priznamo da i sami volimo pistaciju, postoji nešto još bolje. Bučine sjemenke pomalo su zapostavljena, a tako dobra namirnica od koje mogu nastati čudesa. Tostirajte",
      "link": "https://www.jutarnji.hr/dobrahrana/recepti/nisu-samo-za-grickanje-namazi-i-paste-od-pistacije-su-super-ali-ovo-je-jos-jeftinije-i-bolje-15718614",
      "published": "2026-06-16T07:47:31.000Z",
      "source": "Jutarnji",
      "category": "general",
      "xml_category": "recepti",
      "tags": [],
      "image": "https://media.jutarnji.hr/images/slike/2026/06/15/f_39113766_1280.jpg?1781599821"
    },
    {
      "id": "index-1",
      "title": "Restoran u Zagrebu pokrenuo akciju: Djeca subotom jedu besplatno",
      "summary": "JEDAN zagrebački restoran tijekom cijelog lipnja nudi pogodnost koja će posebno razveseliti obitelji s djecom - najmlađi gosti subotom mogu jesti besplatno.",
      "link": "https://www.index.hr/food/clanak/restoran-u-zagrebu-pokrenuo-akciju-djeca-subotom-jedu-besplatno/2803303.aspx",
      "published": "2026-06-16T07:20:00.000Z",
      "source": "Index",
      "category": "general",
      "xml_category": "food",
      "tags": [],
      "image": null
    },
    {
      "id": "index-2",
      "title": "Smrznuto ili iz konzerve - što je bolji izbor kod jedne popularne namirnice?",
      "summary": "USPOREDBA smrznutog i konzerviranog kukuruza.",
      "link": "https://www.index.hr/food/clanak/smrznuto-ili-iz-konzerve-sto-je-bolji-izbor-kod-jedne-popularne-namirnice/2803301.aspx",
      "published": "2026-06-16T06:50:00.000Z",
      "source": "Index",
      "category": "general",
      "xml_category": "food",
      "tags": [],
      "image": null
    },
    {
      "id": "index-0",
      "title": "Smrznuti ili konzervirani kukuruz: Koji je bolji izbor?",
      "summary": "USPOREDBA smrznutog i konzerviranog kukuruza.",
      "link": "https://www.index.hr/food/clanak/smrznuti-ili-konzervirani-kukuruz-koji-je-bolji-izbor/2803301.aspx",
      "published": "2026-06-16T06:50:00.000Z",
      "source": "Index",
      "category": "general",
      "xml_category": "food",
      "tags": [],
      "image": null
    },
    {
      "id": "index-3",
      "title": "Lazanje su u Italiji prilično drugačije. A jedan sastojak nikada ne stavljaju",
      "summary": "TALIJANSKI chef otkriva tajne savršenih lazanja.",
      "link": "https://www.index.hr/food/clanak/lazanje-su-u-italiji-prilicno-drugacije-a-jedan-sastojak-nikada-ne-stavljaju/2803295.aspx",
      "published": "2026-06-16T06:37:00.000Z",
      "source": "Index",
      "category": "general",
      "xml_category": "food",
      "tags": [],
      "image": null
    },
    {
      "id": "index-4",
      "title": "Što napraviti da dno pite (opet) ne ispadne gnjecavo?",
      "summary": "SAVJETI za izbjegavanje gnjecave podloge kod pečenja galetta.",
      "link": "https://www.index.hr/food/clanak/sto-napraviti-da-dno-pite-opet-ne-ispadne-gnjecavo/2803284.aspx",
      "published": "2026-06-16T06:03:00.000Z",
      "source": "Index",
      "category": "general",
      "xml_category": "food",
      "tags": [],
      "image": null
    },
    {
      "id": "jutarnji-2",
      "title": "Restoran u centru Zagreba zna biti uzbudljiv, ali ima i onih drugih trenutaka",
      "summary": "Već samim smještajem u atriju Zagrebačkog kazališta mladih, Theatrium by Filho neizbježno ulazi u kazališni registar. Ovdje se od hrane očekuje ritam, režija i barem malo izvedbene preciznosti. Kulinarski projekt chefa Filipa Horvata, jednog od prepoznatljivijih zagrebačkih autora mlađe generacije,.",
      "link": "https://www.jutarnji.hr/dobrahrana/restorani/restoran-u-centru-zagreba-zna-biti-uzbudljiv-ali-ima-i-onih-drugih-trenutaka-15718583",
      "published": "2026-06-16T06:00:00.000Z",
      "source": "Jutarnji",
      "category": "general",
      "xml_category": "restorani",
      "tags": [],
      "image": "https://media.jutarnji.hr/images/slike/2026/06/15/f_36771880_1280.jpg?1781599821"
    },
    {
      "id": "index-5",
      "title": "Amerikanci odabrali omiljeni lanac brze prehrane - poznato i zašto ga biraju",
      "summary": "NOVO istraživanje otkriva da je McDonald's najpopularniji lanac brze hrane u SAD-u.",
      "link": "https://www.index.hr/food/clanak/amerikanci-odabrali-omiljeni-lanac-brze-prehrane-poznato-i-zasto-ga-biraju/2803280.aspx",
      "published": "2026-06-16T05:40:00.000Z",
      "source": "Index",
      "category": "general",
      "xml_category": "food",
      "tags": [],
      "image": null
    },
    {
      "id": "index-0",
      "title": "McDonald's je najpopularniji lanac brze hrane u Americi",
      "summary": "NOVO istraživanje otkriva da je McDonald's najpopularniji lanac brze hrane u SAD-u.",
      "link": "https://www.index.hr/food/clanak/mcdonalds-je-najpopularniji-lanac-brze-hrane-u-americi/2803280.aspx",
      "published": "2026-06-16T05:40:00.000Z",
      "source": "Index",
      "category": "general",
      "xml_category": "food",
      "tags": [],
      "image": null
    },
    {
      "id": "jutarnji-3",
      "title": "Nije svejedno koji oblik tjestenine birate, evo koji ide uz bolonjez i pesto, a koji uz kremaste umake i zapečena jela",
      "summary": "U talijanskoj kuhinji tjestenina nikada nije samo neutralna podloga za umak. Ona je najvažniji dio jela, pažljivo oblikovan element koji ima zadatak nositi, upiti, povezati i naglasiti sve ono što se događa u umaku. Upravo zato se u Italiji ne postavlja pitanje samo \"koji umak?\", nego i \"koja tjeste",
      "link": "https://www.jutarnji.hr/dobrahrana/dobri-savjeti/nije-svejedno-koji-oblik-tjestenine-birate-evo-koji-ide-uz-bolonjez-i-pesto-a-koji-uz-kremaste-umake-i-zapecena-jela-15718569",
      "published": "2026-06-16T05:00:00.000Z",
      "source": "Jutarnji",
      "category": "general",
      "xml_category": "dobri savjeti",
      "tags": [],
      "image": "https://media.jutarnji.hr/images/slike/2026/06/15/f_39113609_1280.jpg?1781599821"
    },
    {
      "id": "jutarnji-4",
      "title": "U Zagrebu se uskoro otvara nova pekarnica, a prije toga, na posebnom druženju moći će se kušati što će točno nuditi",
      "summary": "Kada se prije dva mjeseca počelo šuškati o otvaranju nove pekarnice u Zagrebu, očekivanja su odmah prilično narasla, jer iza projekta Krug bakery stoje iskusna imena. Slastičarka Andona Brajdić je, naime, radila u slovenskim restoranima Strelec i Atelje, ali i u paškom Boškincu, dok je Blaž Rezar ra",
      "link": "https://www.jutarnji.hr/dobrahrana/price/u-zagrebu-se-uskoro-otvara-nova-pekarnica-a-prije-toga-na-posebnom-druzenju-moci-ce-se-kusati-sto-ce-tocno-nuditi-15718556",
      "published": "2026-06-16T04:00:00.000Z",
      "source": "Jutarnji",
      "category": "general",
      "xml_category": "priče",
      "tags": [],
      "image": "https://media.jutarnji.hr/images/slike/2026/06/15/f_39113664_1280.png?1781599821"
    },
    {
      "id": "bon-appetit-0",
      "title": "Easy Homemade Tzatziki Recipe (Greek Yogurt Dip)",
      "summary": "Cool, garlicky, and endlessly versatile, it’s one family tradition worth stealing.",
      "link": "https://www.bonappetit.com/story/tzatziki-sauce-recipe",
      "published": "2026-06-15T22:32:14.000Z",
      "source": "Bon Appetit",
      "category": "general",
      "xml_category": "cooking",
      "tags": [],
      "image": "https://assets.bonappetit.com/photos/64395f49259b5fd1329ed8de/master/pass/20230410-SEO-RECIPES-28660%201.jpg"
    },
    {
      "id": "index-6",
      "title": "Kako pravilno prati jagode da duže ostanu svježe?",
      "summary": "POČELA je sezona jagoda, a s njom i vječno pitanje kako ovo osjetljivo voće što duže sačuvati svježim.",
      "link": "https://www.index.hr/food/clanak/kako-pravilno-prati-jagode-da-duze-ostanu-svjeze/2803195.aspx",
      "published": "2026-06-15T18:27:00.000Z",
      "source": "Index",
      "category": "general",
      "xml_category": "food",
      "tags": [],
      "image": null
    },
    {
      "id": "bon-appetit-1",
      "title": "Paloma",
      "summary": "On a blazing summer day, nothing hits quite like this bubbly, tangy-sweet, and lightly salty tequila cocktail.",
      "link": "https://www.bonappetit.com/recipe/paloma",
      "published": "2026-06-15T17:52:03.000Z",
      "source": "Bon Appetit",
      "category": "general",
      "xml_category": "recipes",
      "tags": [],
      "image": "https://assets.bonappetit.com/photos/62cdd8cedc3e934b224d8fb5/master/pass/0712-paloma-lede.jpg"
    },
    {
      "id": "bon-appetit-2",
      "title": "Miso Curry Beef and Green Beans",
      "summary": "Turn a pound of ground beef into this hearty, umami stir-fry.",
      "link": "https://www.bonappetit.com/recipe/miso-curry-beef-green-beans",
      "published": "2026-06-15T17:00:00.000Z",
      "source": "Bon Appetit",
      "category": "general",
      "xml_category": "recipes",
      "tags": [],
      "image": "https://assets.bonappetit.com/photos/6a20af0958de669c3b8d3413/master/pass/miso-curry-beef-green-beans_RECIPE_V3_060326_4711_VOG_final.jpg"
    },
    {
      "id": "index-7",
      "title": "Šokantne cijene na stadionu u Dallasu za utakmicu Hrvatske i Engleske",
      "summary": "HRVATSKE navijače na Svjetskom prvenstvu u Dallasu očekuju iznimno visoke cijene hrane i pića, znatno više nego u drugim gradovima domaćinima poput Los Angelesa i New Jerseyja.",
      "link": "https://www.index.hr/food/clanak/sokantne-cijene-na-stadionu-u-dallasu-za-utakmicu-hrvatske-i-engleske/2803105.aspx",
      "published": "2026-06-15T13:56:00.000Z",
      "source": "Index",
      "category": "general",
      "xml_category": "food",
      "tags": [],
      "image": null
    },
    {
      "id": "index-8",
      "title": "Koliko često kupovati i kako kuhati? Talijanski chef otkrio trikove za uštedu",
      "summary": "SLAVNI chef Massimo Bottura dijeli kreativne savjete za smanjenje bacanja hrane.",
      "link": "https://www.index.hr/food/clanak/koliko-cesto-kupovati-i-kako-kuhati-talijanski-chef-otkrio-trikove-za-ustedu/2803080.aspx",
      "published": "2026-06-15T12:45:00.000Z",
      "source": "Index",
      "category": "general",
      "xml_category": "food",
      "tags": [],
      "image": null
    },
    {
      "id": "index-9",
      "title": "Najbrži i namirisniji ljetni biskvit koji ćete napraviti",
      "summary": "JEDNOSTAVAN i brz recept za sočan kolač s trešnjama i cimetom.",
      "link": "https://www.index.hr/food/clanak/najbrzi-i-namirisniji-ljetni-biskvit-koji-cete-napraviti/2803066.aspx",
      "published": "2026-06-15T12:31:00.000Z",
      "source": "Index",
      "category": "general",
      "xml_category": "food",
      "tags": [],
      "image": null
    },
    {
      "id": "jutarnji-5",
      "title": "U našem poznatom fast foodu djeca svake subote u lipnju jedu besplatno, evo detalja",
      "summary": "U vremenu u kojem odlazak na ručak ili večeru za cijelu obitelj postaje sve ozbiljniji udar na kućni budžet, svaka ugostiteljska gesta koja pokazuje barem malo razumijevanja za roditelje zaslužuje da se javno pohvali. Upravo je s takvim potezom ovaj lipanj započeo Fish Delish, domaći lanac ribljih f",
      "link": "https://www.jutarnji.hr/dobrahrana/price/u-nasem-poznatom-fast-foodu-djeca-svake-subote-u-lipnju-jedu-besplatno-evo-detalja-15718389",
      "published": "2026-06-15T12:13:00.000Z",
      "source": "Jutarnji",
      "category": "general",
      "xml_category": "priče",
      "tags": [],
      "image": "https://media.jutarnji.hr/images/slike/2026/06/10/f_26761761_1280.jpg?1781599821"
    },
    {
      "id": "index-10",
      "title": "Zaboravite pužiće: Chef rekao koji je tip tjestenine najbolji za salate",
      "summary": "RASPRAVAMA o idealnoj salati od tjestenine došao je kraj. Chef otkrio favorit - i zašto birati baš tu vrstu.",
      "link": "https://www.index.hr/food/clanak/zaboravite-puzice-chef-rekao-koji-je-tip-tjestenine-najbolji-za-salate/2803057.aspx",
      "published": "2026-06-15T11:52:00.000Z",
      "source": "Index",
      "category": "general",
      "xml_category": "food",
      "tags": [],
      "image": null
    },
    {
      "id": "jutarnji-6",
      "title": "Ovaj je festival vina za vikend napunio stari Lovran do posljednjeg kamena",
      "summary": "Ovog vikenda Lovran je ugostio drugo izdanje festivala prirodnih vina Lovran Unfiltered, pod vodstvom ekipe iz Ganeuma, ponajprije Roberta Benzije, Jurice Obrola i Alena Vukića, te Edija Jakupovića iz Peperoncina. Da je festival bio samo dobro organiziran, to bi bilo dovoljno za kratku informativnu.",
      "link": "https://www.jutarnji.hr/dobrahrana/price/ovaj-je-festival-vina-za-vikend-napunio-stari-lovran-do-posljednjeg-kamena-15718324",
      "published": "2026-06-15T10:02:09.000Z",
      "source": "Jutarnji",
      "category": "general",
      "xml_category": "priče",
      "tags": [],
      "image": "https://media.jutarnji.hr/images/slike/2026/06/14/f_39113023_1280.jpg?1781599821"
    },
    {
      "id": "index-11",
      "title": "Par trikova za najbolje sendviče za plažu - pazite što birate",
      "summary": "NAUČITE kako napraviti savršen sendvič za plažu.",
      "link": "https://www.index.hr/food/clanak/par-trikova-za-najbolje-sendvice-za-plazu-pazite-sto-birate/2802981.aspx",
      "published": "2026-06-15T10:02:00.000Z",
      "source": "Index",
      "category": "general",
      "xml_category": "food",
      "tags": [],
      "image": null
    },
    {
      "id": "bon-appetit-3",
      "title": "Fresh Tomato Michelada",
      "summary": "Use summer’s ripest offerings to make this Mexican party bev.",
      "link": "https://www.bonappetit.com/recipe/big-batch-michelada",
      "published": "2026-06-15T10:00:00.000Z",
      "source": "Bon Appetit",
      "category": "general",
      "xml_category": "recipes",
      "tags": [],
      "image": "https://assets.bonappetit.com/photos/6a19a78d1a12f25be8e62b0d/master/pass/big-batch-michelada_PRINT_RECIPE_V1_040126_3910_VOG_test.jpg"
    },
    {
      "id": "bon-appetit-4",
      "title": "Follow These Rules to Avoid a Soggy-Bottom Galette",
      "summary": "You’ll be rewarded with juicy tomato pastries, Bake Club’s recipe of the month.",
      "link": "https://www.bonappetit.com/story/avoid-soggy-bottom-galettes",
      "published": "2026-06-15T10:00:00.000Z",
      "source": "Bon Appetit",
      "category": "general",
      "xml_category": "cooking",
      "tags": [],
      "image": "https://assets.bonappetit.com/photos/6a034d347941910af249d8fd/master/pass/tiny-tomato-galette_LEDE_V3_050626_4823_VOG_NoBadge_final.jpg"
    },
    {
      "id": "index-12",
      "title": "Hrvatska delicija sve je traženija, potražnja je danas deset puta veća",
      "summary": "MEĐU prvim manifestacijama na zadarskom području održana je tradicionalna Dagnjada u Novigradu.",
      "link": "https://www.index.hr/food/clanak/hrvatska-delicija-sve-je-trazenija-potraznja-je-danas-deset-puta-veca/2802959.aspx",
      "published": "2026-06-15T09:38:00.000Z",
      "source": "Index",
      "category": "general",
      "xml_category": "food",
      "tags": [],
      "image": null
    },
    {
      "id": "index-4",
      "title": "U Novigradu se ovog vikenda pojelo 700 kilograma dagnji",
      "summary": "MEĐU prvim manifestacijama na zadarskom području održana je tradicionalna Dagnjada u Novigradu.",
      "link": "https://www.index.hr/food/clanak/u-novigradu-se-ovog-vikenda-pojelo-700-kilograma-dagnji/2802959.aspx",
      "published": "2026-06-15T09:38:00.000Z",
      "source": "Index",
      "category": "general",
      "xml_category": "food",
      "tags": [],
      "image": null
    },
    {
      "id": "index-13",
      "title": "Svi ih kupujemo, ali kako prepoznati dobar - ili loš kroasan?",
      "summary": "SLAVNI slastičar otkriva kako prepoznati savršen kroasan.",
      "link": "https://www.index.hr/food/clanak/svi-ih-kupujemo-ali-kako-prepoznati-dobar-ili-los-kroasan/2802947.aspx",
      "published": "2026-06-15T09:30:00.000Z",
      "source": "Index",
      "category": "general",
      "xml_category": "food",
      "tags": [],
      "image": null
    },
    {
      "id": "jutarnji-7",
      "title": "Ideje za ručak ovog tjedna: Juha od teleće koljenice, topla salata s rižom i tunom i punjena pečena paprika",
      "summary": "Ovog tjedna na našem su se meniju našla tri potpuno različita jela, ali svako od njih nosi neku svoju priču i razlog zbog kojeg bismo ga rado ponovili. Prvo je tu juha od teleće koljenice, jedan od onih recepata koji mirišu na dom i obiteljske ručkove, a čiji okus uvijek nekako najbolje uspijeva u m",
      "link": "https://www.jutarnji.hr/dobrahrana/recepti/ideje-za-rucak-ovog-tjedna-juha-od-telece-koljenice-topla-salata-s-rizom-i-tunom-i-punjena-pecena-paprika-15718297",
      "published": "2026-06-15T09:11:00.000Z",
      "source": "Jutarnji",
      "category": "general",
      "xml_category": "recepti",
      "tags": [],
      "image": "https://media.jutarnji.hr/images/slike/2026/06/14/f_39113180_1280.png?1781599821"
    },
    {
      "id": "index-14",
      "title": "Više volite domaća jela nego ona iz restorana? Postoji znanstveni razlog za to",
      "summary": "ČLANAK objašnjava IKEA efekt, psihološki fenomen zbog kojeg više cijenimo stvari u čiju smo izradu uložili trud.",
      "link": "https://www.index.hr/food/clanak/vise-volite-domaca-jela-nego-ona-iz-restorana-postoji-znanstveni-razlog-za-to/2802937.aspx",
      "published": "2026-06-15T09:06:00.000Z",
      "source": "Index",
      "category": "general",
      "xml_category": "food",
      "tags": [],
      "image": null
    }
  ]
}