{
  "last_updated": "2026-07-20T07:01:11.070Z",
  "source_count": 3,
  "items": [
    {
      "id": "bbc-0",
      "title": "Granny wins care home Happy Hour law change",
      "summary": "Anita Le Brun, the face of a campaign to allow for alcohol to be served at care homes without a licence, is celebrating its success.",
      "link": "https://www.bbc.co.uk/news/videos/c5yrx8347ego?at_medium=RSS&at_campaign=rss",
      "published": "2026-07-20T06:57:55.000Z",
      "source": "BBC",
      "category": "tech",
      "xml_category": "",
      "tags": [],
      "image": "https://ichef.bbci.co.uk/ace/standard/240/cpsprodpb/10c0/live/35605820-8407-11f1-926f-c90d1bcfbc84.jpg"
    },
    {
      "id": "n1-info-4",
      "title": "Jeftino je kupio napušteni otok i stvorio vlastiti raj – danas živi bez struje i vode čak i na -35 °C",
      "summary": "Umjesto da kupi gotovu kuću, posjekao je vlastita stabla na napuštenom otoku i obnovio brvnaru dio po dio, dokazujući da je moguće izgraditi cijeli do",
      "link": "https://n1info.hr/magazin/lifestyle/jeftino-je-kupio-napusteni-otok-i-stvorio-vlastiti-raj-danas-zivi-bez-struje-i-vode-cak-i-na-35-c/",
      "published": "2026-07-20T05:54:40.000Z",
      "source": "N1 Info",
      "category": "general",
      "xml_category": "lifestyle",
      "tags": [],
      "image": "https://n1info.hr/media/images/2026/7/20/1784526700_Snimka_zaslona_2026-07-20_075107.width-1200.jpg"
    },
    {
      "id": "n1-info-8",
      "title": "Kava za jedan euro, ćevapi za pet: Ovo mjesto i dalje ostaje jedna od najpovoljnijih opcija za ljetni odmor",
      "summary": "Dok cijene ljetovanja na brojnim jadranskim destinacijama i dalje rastu, jedno mjesto ostaje među najpovoljnijim opcijama za ljetni odmor.",
      "link": "https://n1info.hr/magazin/lifestyle/kava-za-1-euro-cevapi-za-5-ovo-mjesto-i-dalje-ostaje-jedna-od-najpovoljnijih-opcija-za-ljetni-odmor/",
      "published": "2026-07-20T05:25:22.000Z",
      "source": "N1 Info",
      "category": "tech",
      "xml_category": "lifestyle",
      "tags": [],
      "image": "https://n1info.hr/media/images/2026/7/20/1784524950_PXL_280620_29375582.width-1200.jpg"
    },
    {
      "id": "n1-info-11",
      "title": "Slabljenje sluha: Uzrok, simptomi i kako u cijeloj priči pomaže - umjetna inteligencija?",
      "summary": "Slabljenje sluha jedno je od najuobičajenijih zdravstvenih stanja i vodećih uzroka invaliditeta u suvremenom društvu, koje pogađa čak 1,57 milijardi l",
      "link": "https://n1info.hr/zdravlje/slabljenje-sluha-uzrok-simptomi-i-kako-u-cijeloj-prici-pomaze-umjetna-inteligencija/",
      "published": "2026-07-20T04:55:13.000Z",
      "source": "N1 Info",
      "category": "general",
      "xml_category": "zdravlje",
      "tags": [],
      "image": "https://n1info.hr/media/images/2026/7/13/1783944990_sharon-waldron-Qc88psZd9FU-unsplash.width-1200.jpg"
    },
    {
      "id": "bbc-1",
      "title": "My fitness tracker knew I was pregnant before I did",
      "summary": "Ravika is one of hundreds of women who are noticing early pregnancy signs through the data on their fitness trackers.",
      "link": "https://www.bbc.co.uk/news/articles/cr474z1qyn6o?at_medium=RSS&at_campaign=rss",
      "published": "2026-07-19T23:09:18.000Z",
      "source": "BBC",
      "category": "general",
      "xml_category": "",
      "tags": [],
      "image": "https://ichef.bbci.co.uk/ace/standard/240/cpsprodpb/96bf/live/356d4010-7f8b-11f1-bee8-53ce494e1abc.png"
    },
    {
      "id": "n1-info-19",
      "title": "Prirodni GLP-1: Zaboravite Ozempic, evo kako ga povećati pojedinim namirnicama",
      "summary": "GLP-1 je hormon i dio terapije Ozempica ili Mounjaroa koja se koristi za smanjeni unos hrane, gubitak težine, ali i za tretiranje dijabetesa tipa 1.",
      "link": "https://n1info.hr/zdravlje/prirodni-glp-1-zaboravite-ozempic-evo-kako-ga-povecati-pojedinim-namirnicama/",
      "published": "2026-07-19T19:22:43.000Z",
      "source": "N1 Info",
      "category": "general",
      "xml_category": "zdravlje",
      "tags": [],
      "image": "https://n1info.hr/media/images/2026/7/14/1784030801_rosalind-chang-_jf4UDKcE-U-unsplash.width-1200.jpg"
    },
    {
      "id": "n1-info-16",
      "title": "Protiv njih ste potpuno nemoćni: Pet životinja koje mogu usmrtiti čovjeka za manje od minute",
      "summary": "U prirodi postoje životinje koje zbog svoje snage, brzine ili otrova mogu čovjeku nanijeti smrtonosne ozljede u iznimno kratkom vremenu. Iako su takvi",
      "link": "https://n1info.hr/magazin/lifestyle/protiv-njih-ste-potpuno-nemocni-pet-zivotinja-koje-mogu-usmrtiti-covjeka-za-manje-od-minute/",
      "published": "2026-07-19T19:21:57.000Z",
      "source": "N1 Info",
      "category": "general",
      "xml_category": "lifestyle",
      "tags": [],
      "image": "https://n1info.hr/media/images/2026/7/15/1784117255_pexels-tkirkgoz-5329063.width-1200.jpg"
    },
    {
      "id": "index-0",
      "title": "10 mogućih razloga zbog kojih se brzo debljate",
      "summary": "NENAMJERNO debljanje može biti znak promjena u navikama, stresa, manjka sna, ali i zdravstvenih stanja.",
      "link": "https://www.index.hr/fit/clanak/10-mogucih-razloga-zbog-kojih-se-brzo-debljate/2815286.aspx",
      "published": "2026-07-19T19:20:00.000Z",
      "source": "Index",
      "category": "general",
      "xml_category": "fit",
      "tags": [],
      "image": null
    },
    {
      "id": "n1-info-19",
      "title": "Zaradio 34.000 eura za šest mjeseci uživanja: Evo koji je posao radio",
      "summary": "Nakon završetka škole, fakulteta ili obuke, mnogi mladi ljudi traže neobične karijerne puteve koji se jasno razlikuju od klasičnih uredskih poslova. M",
      "link": "https://n1info.hr/magazin/lifestyle/zaradio-34000-eura-za-sest-mjeseci-uzivanja-evo-koji-je-posao-radio/",
      "published": "2026-07-19T18:42:36.000Z",
      "source": "N1 Info",
      "category": "general",
      "xml_category": "lifestyle",
      "tags": [],
      "image": "https://n1info.hr/media/images/2026/7/19/1784486529_mrkt-waterslide-398249.width-1200.jpg"
    },
    {
      "id": "index-1",
      "title": "Sanjate o tome da se tijekom godišnjeg naspavate? To možda i nije najbolja ideja",
      "summary": "JE LI PAMETNO nadoknađivati san na godišnjem?",
      "link": "https://www.index.hr/fit/clanak/sanjate-o-tome-da-se-tijekom-godisnjeg-naspavate-to-mozda-i-nije-najbolja-ideja/2815260.aspx",
      "published": "2026-07-19T17:04:00.000Z",
      "source": "Index",
      "category": "general",
      "xml_category": "fit",
      "tags": [],
      "image": null
    },
    {
      "id": "index-2",
      "title": "Što učiniti kada pronađete krpelja?",
      "summary": "KRPELJI prenose razne opasne bolesti.",
      "link": "https://www.index.hr/fit/clanak/sto-uciniti-kada-pronadjete-krpelja/2815216.aspx",
      "published": "2026-07-19T13:07:00.000Z",
      "source": "Index",
      "category": "general",
      "xml_category": "fit",
      "tags": [],
      "image": null
    },
    {
      "id": "sciencedaily-health-0",
      "title": "The mysterious hum heard around the world may finally have an explanation",
      "summary": "The mysterious sound known as The Hum has been reported worldwide for decades, yet its source often remains impossible to find. Researchers tested whether people who hear it have exceptional low-frequency hearing or measurable sounds produced inside their ears, but neither explanation fit most parti",
      "link": "https://www.sciencedaily.com/releases/2026/07/260719040002.htm",
      "published": "2026-07-19T12:07:13.000Z",
      "source": "ScienceDaily Health",
      "category": "general",
      "xml_category": "",
      "tags": [],
      "image": null
    },
    {
      "id": "index-3",
      "title": "Što se događa s vašim snom kada jedete visokoproteinski obrok prije spavanja?",
      "summary": "MANJI proteinski obrok prije spavanja može ublažiti glad, ali ne jamči bolji san.",
      "link": "https://www.index.hr/fit/clanak/sto-se-dogadja-s-vasim-snom-kada-jedete-visokoproteinski-obrok-prije-spavanja/2815196.aspx",
      "published": "2026-07-19T11:36:00.000Z",
      "source": "Index",
      "category": "general",
      "xml_category": "fit",
      "tags": [],
      "image": null
    },
    {
      "id": "index-0",
      "title": "Kako visokoproteinski obroci prije spavanja utječu na san?",
      "summary": "MANJI proteinski obrok prije spavanja može ublažiti glad, ali ne jamči bolji san.",
      "link": "https://www.index.hr/fit/clanak/kako-visokoproteinski-obroci-prije-spavanja-utjecu-na-san/2815196.aspx",
      "published": "2026-07-19T11:36:00.000Z",
      "source": "Index",
      "category": "general",
      "xml_category": "fit",
      "tags": [],
      "image": null
    },
    {
      "id": "n1-info-17",
      "title": "Promjena pravila na crnogorskim plažama: Besplatne ležaljke nakon 17 sati, ali više ne za sve",
      "summary": "Dosadašnjih godina ležaljke i suncobrani na plažama u Crnoj Gori bili su besplatni nakon 17 sati za sve posjetitelje, a zakupci plaža bili su obvezni",
      "link": "https://n1info.hr/magazin/lifestyle/promjena-pravila-na-crnogorskim-plazama-besplatne-lezaljke-nakon-17-sati-ali-vise-ne-za-sve/",
      "published": "2026-07-19T11:30:02.000Z",
      "source": "N1 Info",
      "category": "general",
      "xml_category": "lifestyle",
      "tags": [],
      "image": "https://n1info.hr/media/images/2026/7/19/1784460477_ilia-NVy3z5J7ZKE-unsplash.width-1200.jpg"
    },
    {
      "id": "n1-info-18",
      "title": "Ovu pogrešku pri pranju posteljine mnogi rade ljeti, a zbog nje se više znojite tijekom spavanja",
      "summary": "Ako se tijekom ljetnih noći budite oznojeni i imate osjećaj da vam je posteljina teška i neprozračna, razlog možda nije samo u visokim temperaturama.",
      "link": "https://n1info.hr/magazin/lifestyle/ovu-pogresku-pri-pranju-posteljine-mnogi-rade-ljeti-a-zbog-nje-se-vise-znojite-tijekom-spavanja/",
      "published": "2026-07-19T10:04:59.000Z",
      "source": "N1 Info",
      "category": "general",
      "xml_category": "lifestyle",
      "tags": [],
      "image": "https://n1info.hr/media/images/2026/7/19/1784455299_susan-wilkinson-gSOdp7YlgNQ-unsplash.width-1200.jpg"
    },
    {
      "id": "sciencedaily-health-1",
      "title": "Coffee may help the body fight stress and aging through a hidden cellular switch",
      "summary": "Scientists may have uncovered one reason coffee is repeatedly associated with healthier aging and lower disease risk. Compounds in coffee appear to activate NR4A1, a receptor that helps protect cells from stress, inflammation, and damage. These protective effects disappeared when the receptor was re",
      "link": "https://www.sciencedaily.com/releases/2026/07/260719035927.htm",
      "published": "2026-07-19T09:19:13.000Z",
      "source": "ScienceDaily Health",
      "category": "general",
      "xml_category": "",
      "tags": [],
      "image": null
    },
    {
      "id": "n1-info-19",
      "title": "Promatranje divljih životinja novi je hit među putnicima, ove su najpopularnije",
      "summary": "Zaboravite klasične safarije i tradicionalnu \"veliku petorku\". Današnji putnici sve češće sanjaju o susretima s pandama, klokanima, koalama i kitovima",
      "link": "https://n1info.hr/magazin/lifestyle/promatranje-divljih-zivotinja-novi-je-hit-medju-putnicima-ove-su-najpopularnije/",
      "published": "2026-07-19T07:39:51.000Z",
      "source": "N1 Info",
      "category": "general",
      "xml_category": "lifestyle",
      "tags": [],
      "image": "https://n1info.hr/media/images/2026/7/19/1784446583_travis-chen-rbHAnOL5oto-unsplash.width-1200.jpg"
    },
    {
      "id": "index-4",
      "title": "Što jesti za doručak kako bi imali više energije tijekom dana?",
      "summary": "DORUČAK koji osigurava energiju za čitav dan trebao bi kombinirati složene ugljikohidrate, proteine i zdrave masti.",
      "link": "https://www.index.hr/fit/clanak/sto-jesti-za-dorucak-kako-bi-imali-vise-energije-tijekom-dana/2815146.aspx",
      "published": "2026-07-19T07:21:00.000Z",
      "source": "Index",
      "category": "general",
      "xml_category": "fit",
      "tags": [],
      "image": null
    },
    {
      "id": "index-5",
      "title": "Kako svakodnevna konzumacija češnjaka utječe na zdravlje vaše jetre?",
      "summary": "ČEŠNJAK može biti koristan za jetru zbog protuupalnih svojstava.",
      "link": "https://www.index.hr/fit/clanak/kako-svakodnevna-konzumacija-cesnjaka-utjece-na-zdravlje-vase-jetre/2815140.aspx",
      "published": "2026-07-19T07:06:00.000Z",
      "source": "Index",
      "category": "general",
      "xml_category": "fit",
      "tags": [],
      "image": null
    }
  ]
}