{
  "last_updated": "2026-06-10T16:29:03.671Z",
  "source_count": 3,
  "items": [
    {
      "id": "index-0",
      "title": "Hodanje može odgoditi Alzheimerovu bolest za čak sedam godina, pokazuje studija",
      "summary": "ZNANSTVENA studija pokazuje da hodanje između 5000 i 7500 koraka dnevno može odgoditi kognitivno propadanje.",
      "link": "https://www.index.hr/fit/clanak/hodanje-moze-odgoditi-alzheimerovu-bolest-za-cak-sedam-godina-pokazuje-studija/2801317.aspx",
      "published": "2026-06-10T14:57:00.000Z",
      "source": "Index",
      "category": "general",
      "xml_category": "fit",
      "tags": [],
      "image": null
    },
    {
      "id": "index-1",
      "title": "Video koji bi pušače mogao natjerati da ostave cigarete",
      "summary": "SIMULACIJA prikazuje kako pušenje nepovratno uništava pluća.",
      "link": "https://www.index.hr/fit/clanak/video-koji-bi-pusace-mogao-natjerati-da-ostave-cigarete/2801227.aspx",
      "published": "2026-06-10T12:41:00.000Z",
      "source": "Index",
      "category": "general",
      "xml_category": "fit",
      "tags": [],
      "image": null
    },
    {
      "id": "index-0",
      "title": "Simulacija pokazuje što cigarete rade plućima, mnoge je natjerala na razmišljanje",
      "summary": "SIMULACIJA prikazuje kako pušenje nepovratno uništava pluća.",
      "link": "https://www.index.hr/fit/clanak/simulacija-pokazuje-sto-cigarete-rade-plucima-mnoge-je-natjerala-na-razmisljanje/2801227.aspx",
      "published": "2026-06-10T12:41:00.000Z",
      "source": "Index",
      "category": "general",
      "xml_category": "fit",
      "tags": [],
      "image": null
    },
    {
      "id": "index-2",
      "title": "Skrivene navike koje ubrzavaju starenje i štete zdravlju",
      "summary": "SVAKODNEVNE navike poput stresa, dehidracije i sjedilačkog načina života ubrzavaju starenje.",
      "link": "https://www.index.hr/fit/clanak/skrivene-navike-koje-ubrzavaju-starenje-i-stete-zdravlju/2801197.aspx",
      "published": "2026-06-10T12:07:00.000Z",
      "source": "Index",
      "category": "general",
      "xml_category": "fit",
      "tags": [],
      "image": null
    },
    {
      "id": "index-3",
      "title": "Istraživanje: Jedan avokado dnevno pomaže u regulaciji šećera u krvi",
      "summary": "JEDAN avokado dnevno može pomoći u regulaciji šećera u krvi i smanjiti rizik od dijabetesa, pokazalo je novo istraživanje.",
      "link": "https://www.index.hr/fit/clanak/istrazivanje-jedan-avokado-dnevno-pomaze-u-regulaciji-secera-u-krvi/2801128.aspx",
      "published": "2026-06-10T10:19:00.000Z",
      "source": "Index",
      "category": "general",
      "xml_category": "fit",
      "tags": [],
      "image": null
    },
    {
      "id": "index-4",
      "title": "Pet ultraprerađenih namirnica koje nutricionistica nikada ne kupuje",
      "summary": "POZNATA nutricionistica otkrila je 5 ultraprerađenih namirnica koje nikad ne kupuje.",
      "link": "https://www.index.hr/fit/clanak/pet-ultrapreradjenih-namirnica-koje-nutricionistica-nikada-ne-kupuje/2801083.aspx",
      "published": "2026-06-10T09:10:00.000Z",
      "source": "Index",
      "category": "general",
      "xml_category": "fit",
      "tags": [],
      "image": null
    },
    {
      "id": "index-5",
      "title": "Zašto Ozempic nekima ne pomaže?",
      "summary": "STUDIJA otkrila zašto lijekovi poput Ozempica kod nekih ljudi slabije djeluju.",
      "link": "https://www.index.hr/fit/clanak/zasto-ozempic-nekima-ne-pomaze/2801068.aspx",
      "published": "2026-06-10T08:42:00.000Z",
      "source": "Index",
      "category": "general",
      "xml_category": "fit",
      "tags": [],
      "image": null
    },
    {
      "id": "index-1",
      "title": "Nova studija otkriva zašto neki ljudi ne reagiraju na lijekove za mršavljenje",
      "summary": "STUDIJA otkrila zašto lijekovi poput Ozempica kod nekih ljudi slabije djeluju.",
      "link": "https://www.index.hr/fit/clanak/nova-studija-otkriva-zasto-neki-ljudi-ne-reagiraju-na-lijekove-za-mrsavljenje/2801068.aspx",
      "published": "2026-06-10T08:42:00.000Z",
      "source": "Index",
      "category": "general",
      "xml_category": "fit",
      "tags": [],
      "image": null
    },
    {
      "id": "bbc-18",
      "title": "What are the symptoms of prostate cancer and what should you check for?",
      "summary": "One in eight men in the UK will be diagnosed with prostate cancer in their lifetime.",
      "link": "https://www.bbc.com/news/articles/cx2plvp341jo?at_medium=RSS&at_campaign=rss",
      "published": "2026-06-10T08:26:23.000Z",
      "source": "BBC",
      "category": "health",
      "xml_category": "",
      "tags": [],
      "image": "https://ichef.bbci.co.uk/ace/standard/240/cpsprodpb/91dc/live/68492b60-5aa7-11f1-b277-cd187c78657d.jpg"
    },
    {
      "id": "index-6",
      "title": "Tuširanje ujutro ili navečer? Znanost ima jasan odgovor",
      "summary": "VJEČNO pitanje oko kojeg se lome koplja glasi: je li se bolje tuširati ujutro ili navečer?",
      "link": "https://www.index.hr/fit/clanak/tusiranje-ujutro-ili-navecer-znanost-ima-jasan-odgovor/2801025.aspx",
      "published": "2026-06-10T07:54:00.000Z",
      "source": "Index",
      "category": "general",
      "xml_category": "fit",
      "tags": [],
      "image": null
    },
    {
      "id": "index-7",
      "title": "Kraljica Camilla svaki dan jede isti doručak koji snižava kolesterol i čuva srce",
      "summary": "OVO JELO, bogato beta-glukanom, dokazano pomaže u snižavanju kolesterola i čuva zdravlje srca.",
      "link": "https://www.index.hr/fit/clanak/kraljica-camilla-svaki-dan-jede-isti-dorucak-koji-snizava-kolesterol-i-cuva-srce/2800979.aspx",
      "published": "2026-06-10T06:14:00.000Z",
      "source": "Index",
      "category": "general",
      "xml_category": "fit",
      "tags": [],
      "image": null
    },
    {
      "id": "n1-info-17",
      "title": "Češete ubod komarca? Stručnjaci otkrili što se tada događa ispod kože i zašto radite opasnu pogrešku",
      "summary": "Češanje uboda komarca pojačava svrbež i otvara ranicu, umjesto da je smiri.",
      "link": "https://n1info.hr/magazin/lifestyle/cesete-ubod-komarca-strucnjaci-otkrili-sto-se-tada-dogadja-ispod-koze-i-zasto-radite-opasnu-pogresku/",
      "published": "2026-06-10T06:09:18.000Z",
      "source": "N1 Info",
      "category": "general",
      "xml_category": "lifestyle",
      "tags": [],
      "image": "https://n1info.hr/media/images/1725795817-mosquito-213805_1920.width-1200.jpg"
    },
    {
      "id": "sciencedaily-health-0",
      "title": "Popular joint supplement glucosamine linked to faster Alzheimer’s progression",
      "summary": "A major study suggests glucosamine, a popular supplement for joint pain, could be linked to faster progression from mild cognitive impairment to Alzheimer’s disease. Researchers found a 25% higher likelihood of developing dementia among glucosamine users and uncovered biological clues that may expla",
      "link": "https://www.sciencedaily.com/releases/2026/06/260610003044.htm",
      "published": "2026-06-10T05:17:56.000Z",
      "source": "ScienceDaily Health",
      "category": "general",
      "xml_category": "",
      "tags": [],
      "image": null
    },
    {
      "id": "n1-info-15",
      "title": "Ova tri astrološka znaka dobit će povišicu, a razlog za to je jednostavan",
      "summary": "Prema astrološkim predviđanjima, trima horoskopskim znakovima uskoro se smiješi povišica, a stanje na njihovom računu trebalo bi se dodatno poboljšava",
      "link": "https://n1info.hr/magazin/lifestyle/ova-tri-astroloska-znaka-dobit-ce-povisicu-a-razlog-za-to-je-jednostavan/",
      "published": "2026-06-10T04:35:44.000Z",
      "source": "N1 Info",
      "category": "general",
      "xml_category": "lifestyle",
      "tags": [],
      "image": "https://n1info.hr/media/images/1732703052-alexander-grey-rItGZ4vquWk-unsplash.width-1200.jpg"
    },
    {
      "id": "sciencedaily-health-4",
      "title": "Cancer patients found a simple way to stay mentally sharp during chemotherapy",
      "summary": "“Chemo brain” affects up to 80% of people receiving chemotherapy, making everyday tasks harder. In a new trial, cancer patients who followed a home-based exercise program showed better attention and fewer noticeable cognitive problems than those who received a placebo. Low-dose ibuprofen also improv",
      "link": "https://www.sciencedaily.com/releases/2026/06/260608040019.htm",
      "published": "2026-06-10T01:16:16.000Z",
      "source": "ScienceDaily Health",
      "category": "health",
      "xml_category": "",
      "tags": [],
      "image": null
    },
    {
      "id": "bbc-0",
      "title": "Advanced radiotherapy for prostate cancer to cut sessions from 20 to five",
      "summary": "Some men in England with the disease will now be offered an advanced form of treatment on the NHS.",
      "link": "https://www.bbc.com/news/articles/crm02mmgr3ro?at_medium=RSS&at_campaign=rss",
      "published": "2026-06-09T23:57:30.000Z",
      "source": "BBC",
      "category": "health",
      "xml_category": "",
      "tags": [],
      "image": "https://ichef.bbci.co.uk/ace/standard/240/cpsprodpb/2337/live/461b52a0-6490-11f1-8546-8f19e4fe30f4.jpg"
    },
    {
      "id": "n1-info-17",
      "title": "Financijski alarm za 3 znaka: Dolaze neočekivani troškovi",
      "summary": "Druga polovica lipnja mnogima će donijeti nove prilike za zaradu, napredovanje i poboljšanje financijske situacije. Ipak, astrolozi upozoravaju da će",
      "link": "https://n1info.hr/magazin/lifestyle/financijski-alarm-za-3-znaka-dolaze-neocekivani-troskovi/",
      "published": "2026-06-09T19:55:42.000Z",
      "source": "N1 Info",
      "category": "general",
      "xml_category": "lifestyle",
      "tags": [],
      "image": "https://n1info.hr/media/images/2026/6/4/1780573064_jakub-zerdzicki-ESd6ElfxRW0-unsplash.width-1200.jpg"
    },
    {
      "id": "index-8",
      "title": "Kako Victoria Beckham održava liniju? Već 25 godina jede isto",
      "summary": "VICTORIA Beckham već 25 godina jede isto: ribu s grila i povrće na pari.",
      "link": "https://www.index.hr/fit/clanak/kako-victoria-beckham-odrzava-liniju-vec-25-godina-jede-isto/2800871.aspx",
      "published": "2026-06-09T18:11:00.000Z",
      "source": "Index",
      "category": "general",
      "xml_category": "fit",
      "tags": [],
      "image": null
    },
    {
      "id": "index-9",
      "title": "Čuli ste da treba spavati minimalno osam sati? Studija donosi nove podatke",
      "summary": "NOVO istraživanje otkriva da je optimalna količina sna za usporavanje starenja između 6,4 i 7,8 sati.",
      "link": "https://www.index.hr/fit/clanak/culi-ste-da-treba-spavati-minimalno-osam-sati-studija-donosi-nove-podatke/2800863.aspx",
      "published": "2026-06-09T17:38:00.000Z",
      "source": "Index",
      "category": "general",
      "xml_category": "fit",
      "tags": [],
      "image": null
    },
    {
      "id": "n1-info-15",
      "title": "Od kraljevskog vjenčanja do filmskog turizma: Što je brendiranje nacija i koje su zemlje uspješni primjeri?",
      "summary": "Olimpijske igre, vjenčanje princa Williama i princeze Kate, talijanska kuhinja, rođendan kraljice i Gospodar prstenova – na prvi pogled nemaju gotovo",
      "link": "https://n1info.hr/magazin/lifestyle/od-kraljevskog-vjencanja-do-filmskog-turizma-sto-je-brendiranje-nacija-i-koje-su-zemlje-uspjesni-primjeri/",
      "published": "2026-06-09T17:31:23.000Z",
      "source": "N1 Info",
      "category": "general",
      "xml_category": "lifestyle",
      "tags": [],
      "image": "https://n1info.hr/media/images/2026/6/8/1780905638_paddington_AFP.width-1200.jpg"
    }
  ]
}